streamlit_pages/__init__.py
streamlit_pages/streamlit_pages.py
streamlit_pages-0.1.0.dist-info/LICENSE
streamlit_pages-0.1.0.dist-info/WHEEL
streamlit_pages-0.1.0.dist-info/METADATA
streamlit_pages-0.1.0.dist-info/RECORD
