Metadata-Version: 2.1
Name: streamlit-pages
Version: 0.1.0
Summary: Addons like multipages for streamlit webapp
Home-page: https://github.com/bvenkatesh-ai/streamlit_pages
License: MIT
Author: Venkatesh Boddu
Requires-Python: >=3.6,<4.0
Classifier: License :: OSI Approved :: MIT License
Classifier: Programming Language :: Python :: 3
Classifier: Programming Language :: Python :: 3.6
Classifier: Programming Language :: Python :: 3.7
Classifier: Programming Language :: Python :: 3.8
Classifier: Programming Language :: Python :: 3.9
Requires-Dist: streamlit (>=0.84,<0.85)
Project-URL: Documentation, https://streamlit_pages.readthedocs.io/en/latest/
Project-URL: Repository, https://github.com/bvenkatesh-ai/streamlit_pages
